<?xml version="1.0" encoding="UTF-8"?>
<!DOCTYPE suite SYSTEM "http://testng.org/testng-1.0.dtd">
<suite name="Timeout Suit">

    <test verbose="2" preserve-order="true" name="TimeOut">
        <classes>
            <class name="clarusway.tests.C05_TimeOut">

                <methods>
                    <include name="test01"/>
                    <include name="test02"/>
                    <include name="test03"/>
                </methods>

            </class>
        </classes>
    </test>

</suite>